CHANGES.rst
COPYING.txt
MANIFEST.in
README.rst
setup.cfg
setup.py
sqlalchemy_pervasive/__init__.py
sqlalchemy_pervasive/_version.py
sqlalchemy_pervasive/base.py
sqlalchemy_pervasive/pyodbc.py
sqlalchemy_pervasive.egg-info/PKG-INFO
sqlalchemy_pervasive.egg-info/SOURCES.txt
sqlalchemy_pervasive.egg-info/dependency_links.txt
sqlalchemy_pervasive.egg-info/entry_points.txt
sqlalchemy_pervasive.egg-info/requires.txt
sqlalchemy_pervasive.egg-info/top_level.txt