Metadata-Version: 1.1
Name: sqlalchemy-pervasive
Version: 0.1.2
Summary: SQLAlchemy Dialect for Pervasive PSQL
Home-page: UNKNOWN
Author: Sacramento Natural Foods Co-op, Inc
Author-email: developer@sacfoodcoop.com
License: GNU GPL v3
Platform: UNKNOWN
Classifier: Development Status :: 3 - Alpha
Classifier: Intended Audience :: Developers
Classifier: License :: OSI Approved :: GNU General Public License v3 or later (GPLv3+)
Classifier: Natural Language :: English
Classifier: Operating System :: OS Independent
Classifier: Programming Language :: Python
Classifier: Programming Language :: Python :: 2.6
Classifier: Programming Language :: Python :: 2.7
Classifier: Topic :: Software Development :: Libraries :: Python Modules
